RTL/mac_gating_2/verilog/clk_gate.v
module clk_gate(clk, en, gated_clk);

input clk;
input en;
output gated_clk;

reg en_latch;

always@(negedge clk)begin

en_latch <= en;

end

assign gated_clk = en_latch && clk;

endmodule

RTL/mac_gating_2/clk_gate_tb.v
module clk_gate_tb;

reg clk;
reg en;
wire gated_clk;

clk_gate DUT(
.clk(clk),
.en(en),
.gated_clk(gated_clk)
);

initial begin

  $dumpfile("clk_gate_tb.vcd");
  $dumpvars(0,clk_gate_tb);
#0.5 clk = 1;
#0.5 clk = 0;
#0.5 clk = 1;
#0.5 clk = 0;
#0.5 clk = 1;
#0.5 clk = 0;
#0.5 clk = 1;
#0.5 clk = 0; en =1;
#0.5 clk = 1;
#0.5 clk = 0;
#0.5 clk = 1;
#0.5 clk = 0;
#0.5 clk = 1;
#0.5 clk = 0;
#0.5 clk = 1;
#0.5 clk = 0;
#0.5 clk = 1;
#0.5 clk = 0;
#0.5 clk = 1;
#0.5 clk = 0;
#0.5 clk = 1;
#0.5 clk = 0;
#0.5 clk = 1;
#0.5 clk = 0;
#0.5 clk = 1;
#0.5 clk = 0;
#0.5 clk = 1;en = 0;
#0.5 clk = 0;
#0.5 clk = 1;en = 1;
#0.5 clk = 0;
#0.5 clk = 1;
#0.5 clk = 0;en = 0;
#0.5 clk = 1;
#0.5 clk = 0;
#0.5 clk = 1;
#0.5 clk = 0;
#0.5 clk = 1;
#0.5 clk = 0;
#0.5 clk = 1;en = 1;
#0.5 clk = 0;
#0.5 clk = 1;
#0.5 clk = 0;
#0.5 clk = 1;
#0.5 clk = 0;
#0.5 clk = 1;
#0.5 clk = 0;
#0.5 clk = 1;
#0.5 clk = 0;
#0.5 clk = 1;
#0.5 clk = 0;
#0.5 clk = 1;
#0.5 clk = 0;
#0.5 clk = 1;
#0.5 clk = 0;
#0.5 clk = 1;
#0.5 clk = 0;
#0.5 clk = 1;
#0.5 clk = 0;
#0.5 clk = 1;
#0.5 clk = 0;
#0.5 clk = 1;
#0.5 clk = 0;
#0.5 clk = 1;
#0.5 clk = 0;


$finish;

end


endmodule

RTL/mac_gating_2/clk_gate_tb.vcd
$date
	Thu Mar 13 18:55:03 2025
$end
$version
	Icarus Verilog
$end
$timescale
	1s
$end
$scope module clk_gate_tb $end
$var wire 1 ! gated_clk $end
$var reg 1 " clk $end
$var reg 1 # en $end
$scope module DUT $end
$var wire 1 " clk $end
$var wire 1 # en $end
$var wire 1 ! gated_clk $end
$var reg 1 $ en_latch $end
$upscope $end
$upscope $end
$enddefinitions $end
#0
$dumpvars
x$
x#
x"
x!
$end
#1
1"
#2
0!
0"
#3
x!
1"
#4
0!
0"
#5
x!
1"
#6
0!
0"
#7
x!
1"
#8
1$
0!
1#
0"
#9
1!
1"
#10
0!
0"
#11
1!
1"
#12
0!
0"
#13
1!
1"
#14
0!
0"
#15
1!
1"
#16
0!
0"
#17
1!
1"
#18
0!
0"
#19
1!
1"
#20
0!
0"
#21
1!
1"
#22
0!
0"
#23
1!
1"
#24
0!
0"
#25
1!
1"
#26
0!
0"
#27
1!
0#
1"
#28
0$
0!
0"
#29
1#
1"
#30
1$
0"
#31
1!
1"
#32
0$
0!
0#
0"
#33
1"
#34
0"
#35
1"
#36
0"
#37
1"
#38
0"
#39
1#
1"
#40
1$
0"
