RTL/mac_gating_2/verilog/mac_input_pipeline.v
module mac_input_pipeline(clk, reset, in_in, inst_in, in_out, inst_out, q_zero);

parameter col = 8;
parameter bw = 8;
parameter bw_psum = 2*bw+6;
parameter pr = 8;

input  clk;
input  [pr*bw-1:0] in_in;
input  reset;
input  [1:0] inst_in; // [1]: execute, [0]: load 

output  reg [pr*bw-1:0] in_out;
output  reg [1:0] inst_out; // [1]: execute, [0]: load 
output  reg [pr-1:0] q_zero;

reg  [pr*bw-1:0] in_out_reg;
reg  [1:0] inst_out_reg; // [1]: execute, [0]: load 

wire [bw-1:0] q_zero_0;
wire [bw-1:0] q_zero_1;
wire [bw-1:0] q_zero_2;
wire [bw-1:0] q_zero_3;
wire [bw-1:0] q_zero_4;
wire [bw-1:0] q_zero_5;
wire [bw-1:0] q_zero_6;
wire [bw-1:0] q_zero_7;



always@(posedge clk) begin
	if(reset) begin
	in_out <= 64'd0;
	inst_out <= 2'b00;
	q_zero <= 8'd0;
	in_out_reg <= 64'd0;
	inst_out_reg <= 2'b00;
        end
	else begin
	q_zero[0] <= q_zero_0;
	q_zero[1] <= q_zero_1;
	q_zero[2] <= q_zero_2;
	q_zero[3] <= q_zero_3;
	q_zero[4] <= q_zero_4;
	q_zero[5] <= q_zero_5;
	q_zero[6] <= q_zero_6;
	q_zero[7] <= q_zero_7;

	in_out_reg <= in_in;
	inst_out_reg <= inst_in;

	in_out <= in_out_reg;
	inst_out <= inst_out_reg;
	
	//in_out <= in_in;
	//inst_out <= inst_in;
	end
end

assign q_zero_0 = ~|in_in[bw*1-1: bw*0];
assign q_zero_1 = ~|in_in[bw*2-1: bw*1];
assign q_zero_2 = ~|in_in[bw*3-1: bw*2];
assign q_zero_3 = ~|in_in[bw*4-1: bw*3];
assign q_zero_4 = ~|in_in[bw*5-1: bw*4];
assign q_zero_5 = ~|in_in[bw*6-1: bw*5];
assign q_zero_6 = ~|in_in[bw*7-1: bw*6];
assign q_zero_7 = ~|in_in[bw*8-1: bw*7];

endmodule

RTL/mac_gating_2/mac_input_pipeline_tb.v
module mac_input_pipeline_tb;

reg  clk;
reg  [63:0] in_in;
reg  reset;
reg  [1:0] inst_in; // [1]: execute, [0]: load 

wire   [63:0] in_out;
wire   [1:0] inst_out; // [1]: execute, [0]: load 
wire   [7:0] q_zero;

reg [63:0] out_in_out;
reg [1:0] out_inst_out;
reg [7:0] out_q_zero;

mac_input_pipeline DUT(
.clk(clk),
.reset(reset),
.in_in(in_in),
.inst_in(inst_in),
.in_out(in_out),
.inst_out(inst_out),
.q_zero(q_zero)

);

initial begin

  $dumpfile("mac_input_pipeline_tb.vcd");
  $dumpvars(0,mac_input_pipeline_tb);
clk = 1;
reset = 0;
inst_in = 0;
in_in = 0;

#0.5 clk = 0;
#0.5 clk = 1;
#0.5 clk = 0; reset = 1;
#0.5 clk = 1;
#0.5 clk = 0;
#0.5 clk = 1;
#0.5 clk = 0; reset = 0;
#0.5 clk = 1;
#0.5 clk = 0;
#0.5 clk = 1;
#0.5 clk = 0; in_in = 64'hAA_89_32_87_D4_76_90_33;
#0.5 clk = 1;
#0.5 clk = 0;in_in = 64'hAA_89_32_87_D4_76_90_33;
#0.5 clk = 1;
#0.5 clk = 0;in_in = 64'hAA_00_32_33_D4_89_EE_33;
#0.5 clk = 1;
#0.5 clk = 0;in_in = 64'hAA_89_32_00_D4_00_00_33;
#0.5 clk = 1;
#0.5 clk = 0; in_in = 64'hAA_89_32_87_D4_76_90_33;
#0.5 clk = 1;
#0.5 clk = 0;in_in = 64'hD0_00_00_33_D4_19_EE_00;
#0.5 clk = 1;
#0.5 clk = 0;in_in = 64'hAA_00_32_33_D4_89_EE_33;
#0.5 clk = 1;
#0.5 clk = 0;
#0.5 clk = 1;
#0.5 clk = 0;
#0.5 clk = 1;
#0.5 clk = 0;
#0.5 clk = 1;
#0.5 clk = 0;
#0.5 clk = 1;


end

always@(posedge clk) begin

out_in_out <= in_out;
out_inst_out <= inst_out;
out_q_zero <= q_zero;

end


endmodule

RTL/mac_gating_2/mac_input_pipeline_tb.vcd
$date
	Thu Mar 13 19:34:33 2025
$end
$version
	Icarus Verilog
$end
$timescale
	1s
$end
$scope module mac_input_pipeline_tb $end
$var wire 8 ! q_zero [7:0] $end
$var wire 2 " inst_out [1:0] $end
$var wire 64 # in_out [63:0] $end
$var reg 1 $ clk $end
$var reg 64 % in_in [63:0] $end
$var reg 2 & inst_in [1:0] $end
$var reg 64 ' out_in_out [63:0] $end
$var reg 2 ( out_inst_out [1:0] $end
$var reg 8 ) out_q_zero [7:0] $end
$var reg 1 * reset $end
$scope module DUT $end
$var wire 1 $ clk $end
$var wire 64 + in_in [63:0] $end
$var wire 2 , inst_in [1:0] $end
$var wire 1 * reset $end
$var wire 8 - q_zero_7 [7:0] $end
$var wire 8 . q_zero_6 [7:0] $end
$var wire 8 / q_zero_5 [7:0] $end
$var wire 8 0 q_zero_4 [7:0] $end
$var wire 8 1 q_zero_3 [7:0] $end
$var wire 8 2 q_zero_2 [7:0] $end
$var wire 8 3 q_zero_1 [7:0] $end
$var wire 8 4 q_zero_0 [7:0] $end
$var reg 64 5 in_out [63:0] $end
$var reg 64 6 in_out_reg [63:0] $end
$var reg 2 7 inst_out [1:0] $end
$var reg 2 8 inst_out_reg [1:0] $end
$var reg 8 9 q_zero [7:0] $end
$upscope $end
$upscope $end
$enddefinitions $end
#0
$dumpvars
bx 9
b0 8
bx 7
b0 6
bx 5
b1 4
b1 3
b1 2
b1 1
b1 0
b1 /
b1 .
b1 -
b0 ,
b0 +
0*
bx )
bx (
bx '
b0 &
b0 %
1$
bx #
bx "
bx !
$end
#1
0$
#2
b0 "
b0 7
b0 #
b0 5
b11111111 !
b11111111 9
1$
#3
1*
0$
#4
b0 !
b0 9
b11111111 )
b0 (
b0 '
1$
#5
0$
#6
b0 )
1$
#7
0*
0$
#8
b11111111 !
b11111111 9
1$
#9
0$
#10
b11111111 )
1$
#11
b0 4
b0 3
b0 2
b0 1
b0 0
b0 /
b0 .
b0 -
b1010101010001001001100101000011111010100011101101001000000110011 %
b1010101010001001001100101000011111010100011101101001000000110011 +
0$
#12
b1010101010001001001100101000011111010100011101101001000000110011 6
b0 !
b0 9
1$
#13
0$
#14
b0 )
b1010101010001001001100101000011111010100011101101001000000110011 #
b1010101010001001001100101000011111010100011101101001000000110011 5
1$
#15
b1 .
b1010101000000000001100100011001111010100100010011110111000110011 %
b1010101000000000001100100011001111010100100010011110111000110011 +
0$
#16
b1010101000000000001100100011001111010100100010011110111000110011 6
b1000000 !
b1000000 9
b1010101010001001001100101000011111010100011101101001000000110011 '
1$
#17
b1 3
b1 2
b1 0
b0 .
b1010101010001001001100100000000011010100000000000000000000110011 %
b1010101010001001001100100000000011010100000000000000000000110011 +
0$
#18
b1000000 )
b1010101000000000001100100011001111010100100010011110111000110011 #
b1010101000000000001100100011001111010100100010011110111000110011 5
b1010101010001001001100100000000011010100000000000000000000110011 6
b10110 !
b10110 9
1$
#19
b0 3
b0 2
b0 0
b1010101010001001001100101000011111010100011101101001000000110011 %
b1010101010001001001100101000011111010100011101101001000000110011 +
0$
#20
b1010101010001001001100100000000011010100000000000000000000110011 #
b1010101010001001001100100000000011010100000000000000000000110011 5
b1010101010001001001100101000011111010100011101101001000000110011 6
b0 !
b0 9
b10110 )
b1010101000000000001100100011001111010100100010011110111000110011 '
1$
#21
b1 4
b1 /
b1 .
b1101000000000000000000000011001111010100000110011110111000000000 %
b1101000000000000000000000011001111010100000110011110111000000000 +
0$
#22
b0 )
b1010101010001001001100100000000011010100000000000000000000110011 '
b1010101010001001001100101000011111010100011101101001000000110011 #
b1010101010001001001100101000011111010100011101101001000000110011 5
b1101000000000000000000000011001111010100000110011110111000000000 6
b1100001 !
b1100001 9
1$
#23
b0 4
b0 /
b1010101000000000001100100011001111010100100010011110111000110011 %
b1010101000000000001100100011001111010100100010011110111000110011 +
0$
#24
b1101000000000000000000000011001111010100000110011110111000000000 #
b1101000000000000000000000011001111010100000110011110111000000000 5
b1010101000000000001100100011001111010100100010011110111000110011 6
b1000000 !
b1000000 9
b1100001 )
b1010101010001001001100101000011111010100011101101001000000110011 '
1$
#25
0$
#26
b1000000 )
b1101000000000000000000000011001111010100000110011110111000000000 '
b1010101000000000001100100011001111010100100010011110111000110011 #
b1010101000000000001100100011001111010100100010011110111000110011 5
1$
#27
0$
#28
b1010101000000000001100100011001111010100100010011110111000110011 '
1$
