RTL/controller/verilog/controller.v
module controller(clk, reset, start, q_full, k_full, ld_done, ofifo_wr, ofifo_full, sfp_ready, int_fifo_full, inst, done );

input clk;
input reset;
input start;

input q_full;  // Q SRAM is full
input k_full;  // K SRAM is full
input ld_done; // extract ld_ready_q from each mac column and NOR them to exit the LOAD stage
input ofifo_wr; // AND all the ofifo_wr signals from each mac col to exit exec stage
input ofifo_full; //o_full signal from ofifo
input sfp_ready;
input int_fifo_full;

output reg [18:0] inst;
output done;

reg [3:0] current_state;
reg [3:0] nxt_state;

//States
// 0000  - 0 //idle
// 0001  - 1 //q write
// 0010  - 2 //k write
// 0011  - 3 //k load
// 0100  - 4 //exec
// 0101  - 5 //ofifo_write
// 0110  - 6 //sfp_accum
// 0111  - 7 //sfp _hold
// 1000  - 8 //sfp_div
// 1001  - 9 //write_pmem
//
//



/*
assign inst[18:17] = sfp something;
assign inst[16] = ofifo_rd;
assign inst[15:12] = qkmem_add;
assign inst[11:8]  = pmem_add;
assign inst[7] = execute;
assign inst[6] = load;
assign inst[5] = qmem_rd;
assign inst[4] = qmem_wr;
assign inst[3] = kmem_rd;
assign inst[2] = kmem_wr;
assign inst[1] = pmem_rd;
assign inst[0] = pmem_wr;
*/

reg [4:0] counter;


localparam IDLE = 4'b0000,
           Q_WRITE = 4'b0001,
           K_WRITE = 4'b0010,
           K_LOAD= 4'b0011,
           EXEC = 4'b0100,
           OFIFO_WRITE = 4'b0101,
           SFP_ACCUM = 4'b0110,
           SFP_HOLD = 4'b0111,
           SFP_DIV = 4'b1000,
           WRITE_PMEM = 4'b1001;

always @(posedge clk)
begin

    if (reset) begin
    	current_state <= IDLE;
    	nxt_state     <= IDLE;
	counter       <= {{1'b0},{IDLE}};
	inst          <= 19'd0;
    end
    else begin
	    
    current_state <= nxt_state;

    
    case(current_state)
	    IDLE : if(start) nxt_state <= Q_WRITE; 
	
	    Q_WRITE : begin
		    if(~q_full) begin
		    	inst[4]     <= 1'b1; 
		    	inst[15:12] <= counter[3:0];
			counter     <= counter + 1;
		end else begin 
			nxt_state   <= K_WRITE;
		        counter     <= 5'b00000;
			inst[15:12] <= 4'b0000;
			inst[4]     <= 1'b0;
		    end
	            end
            K_WRITE : begin
		    if(~k_full) begin
		    	inst[2]     <= 1'b1; 
		    	inst[15:12] <= counter[3:0];
			counter     <= counter + 1;
		    end else begin
			nxt_state   <= K_LOAD;
		        counter     <= 5'b00000;
			inst[15:12] <= 4'b0000;
			inst[2]     <= 1'b0;
		    end
	            end
	    K_LOAD: begin
		    if(inst[6] == 0) inst[6] <= 1'b1;
		    else if(inst[6]) begin
			if(~ld_done) begin   
		    		inst[3]     <= 1'b1; 
		    		inst[15:12] <= counter[3:0];
				counter     <= counter + 1;
			end else if(ld_done && ~inst[3] ) begin
				inst[6]     <= 1'b0;
				nxt_state   <= EXEC;
			end else begin
				inst[15:12] <= 4'b0000;
				counter     <= 4'b0000;
				inst[3]     <= 1'b0;
			end
		    end 
         	    end
             EXEC: begin
		    if(~ofifo_wr) begin
		    	inst[5]     <= 1'b1; 
			inst[7]     <= 1'b1;
		    	inst[15:12] <= counter[3:0];
			counter     <= counter + 1;
		    end 		    
		    else begin
			nxt_state   <= OFIFO_WRITE;
		        counter     <= 5'b00000;
			inst[15:12] <= 4'b0000;
			inst[5]     <= 1'b0;
			inst[7]     <= 1'b0;
		    end
             end
	     OFIFO_WRITE: begin
		        if(~ofifo_full) inst 	  <= 19'd0;
			else 		nxt_state <= SFP_ACCUM;

	     end
		    
    endcase

    end

end

assign done = ~|current_state;

endmodule

RTL/controller/verilog/controller_tb.v
module controller_tb;

reg clk;
reg reset;
reg start;

reg q_full;
reg k_full;
reg ld_done;
reg ofifo_wr;
reg ofifo_full;
reg sfp_ready;
reg int_fifo_full;

wire q_full_wire;
wire k_full_wire;
wire ld_done_wire;
wire ofifo_wr_wire;
wire ofifo_full_wire;
wire sfp_ready_wire;
wire int_fifo_full_wire;


wire [18:0] inst;
wire done;

controller DUT(
 .clk(clk),
 .reset(reset),
 .start(start),
 .q_full(q_full),
 .k_full(k_full),
 .ld_done(ld_done),
 .ofifo_wr(ofifo_wr),
 .ofifo_full(ofifo_full),
 .sfp_ready(sfp_ready),
 .int_fifo_full(int_fifo_full),
 .inst(inst),
 .done(done)
);

integer i,j,k,l;

assign q_full_wire = inst[4] & inst[12] & inst[13] & inst[14];
assign k_full_wire = inst[2] & inst[12] & inst[13] & inst[14];
assign ld_done_wire = inst[3] & inst[12] & inst[13] & inst[14];
assign ofifo_wr_wire = inst[5] & inst[7] & inst[12] & inst[13] & inst[14];
//assign ofifo_full_wire = ofifo_wr_wire;

initial begin

  $dumpfile("controller_tb.vcd");
  $dumpvars(0,controller_tb);

clk = 1;
reset = 0;
start = 0;

q_full = 0;
k_full = 0;
ld_done = 0;
ofifo_wr = 0;
ofifo_full = 0;
sfp_ready = 0;
int_fifo_full = 0;

#0.5 clk = 0;
#0.5 clk = 1;
#0.5 clk = 0;reset = 1;
#0.5 clk = 1;
#0.5 clk = 0;
#0.5 clk = 1;
#0.5 clk = 0;reset = 0;
#0.5 clk = 1;
#0.5 clk = 0;
#0.5 clk = 1;
#0.5 clk = 0;start = 1;
#0.5 clk = 1;
#0.5 clk = 0;start = 0;
#0.5 clk = 1;
#0.5 clk = 0;

for(i = 0; i<64; i=i+1) begin
#0.5 clk = 1;
#0.5 clk = 0;
end


$finish;

end

always@(posedge clk) begin
if(q_full_wire) q_full     <= 1'b1;
if(k_full_wire) k_full     <= 1'b1;
if(ld_done_wire) ld_done    <= 1'b1;
if(ofifo_wr_wire) ofifo_wr   <= 1'b1;
if(ofifo_wr_wire) ofifo_full <= 1'b1;


end

endmodule

RTL/controller/controller_tb.vcd
$date
	Sun Mar 16 22:10:21 2025
$end
$version
	Icarus Verilog
$end
$timescale
	1s
$end
$scope module controller_tb $end
$var wire 1 ! k_full_wire $end
$var wire 1 " ld_done_wire $end
$var wire 1 # ofifo_wr_wire $end
$var wire 1 $ q_full_wire $end
$var wire 19 % inst [18:0] $end
$var wire 1 & done $end
$var reg 1 ' clk $end
$var reg 1 ( int_fifo_full $end
$var reg 1 ) k_full $end
$var reg 1 * ld_done $end
$var reg 1 + ofifo_full $end
$var reg 1 , ofifo_wr $end
$var reg 1 - q_full $end
$var reg 1 . reset $end
$var reg 1 / sfp_ready $end
$var reg 1 0 start $end
$var integer 32 1 i [31:0] $end
$scope module DUT $end
$var wire 1 ' clk $end
$var wire 1 ( int_fifo_full $end
$var wire 1 ) k_full $end
$var wire 1 * ld_done $end
$var wire 1 + ofifo_full $end
$var wire 1 , ofifo_wr $end
$var wire 1 - q_full $end
$var wire 1 . reset $end
$var wire 1 / sfp_ready $end
$var wire 1 0 start $end
$var wire 1 & done $end
$var reg 5 2 counter [4:0] $end
$var reg 4 3 current_state [3:0] $end
$var reg 19 4 inst [18:0] $end
$var reg 4 5 nxt_state [3:0] $end
$upscope $end
$upscope $end
$enddefinitions $end
#0
$dumpvars
bx 5
bx 4
bx 3
bx 2
bx 1
00
0/
0.
0-
0,
0+
0*
0)
0(
1'
x&
bx %
x$
x#
x"
x!
$end
#1
0'
#2
1'
#3
1.
0'
#4
0#
0"
0!
0$
b0 %
b0 4
b0 2
b0 5
1&
b0 3
1'
#5
0'
#6
1'
#7
0.
0'
#8
1'
#9
0'
#10
1'
#11
10
0'
#12
b1 5
1'
#13
00
0'
#14
0&
b1 3
1'
#15
b0 1
0'
#16
b1 2
b10000 %
b10000 4
1'
#17
b1 1
0'
#18
b10 2
b1000000010000 %
b1000000010000 4
1'
#19
b10 1
0'
#20
b11 2
b10000000010000 %
b10000000010000 4
1'
#21
b11 1
0'
#22
b100 2
b11000000010000 %
b11000000010000 4
1'
#23
b100 1
0'
#24
b101 2
b100000000010000 %
b100000000010000 4
1'
#25
b101 1
0'
#26
b110 2
b101000000010000 %
b101000000010000 4
1'
#27
b110 1
0'
#28
b111 2
b110000000010000 %
b110000000010000 4
1'
#29
b111 1
0'
#30
1$
b1000 2
b111000000010000 %
b111000000010000 4
1'
#31
b1000 1
0'
#32
0$
b1001 2
b1000000000010000 %
b1000000000010000 4
1-
1'
#33
b1001 1
0'
#34
b0 %
b0 4
b0 2
b10 5
1'
#35
b1010 1
0'
#36
b10 3
1'
#37
b1011 1
0'
#38
b1 2
b100 %
b100 4
1'
#39
b1100 1
0'
#40
b10 2
b1000000000100 %
b1000000000100 4
1'
#41
b1101 1
0'
#42
b11 2
b10000000000100 %
b10000000000100 4
1'
#43
b1110 1
0'
#44
b100 2
b11000000000100 %
b11000000000100 4
1'
#45
b1111 1
0'
#46
b101 2
b100000000000100 %
b100000000000100 4
1'
#47
b10000 1
0'
#48
b110 2
b101000000000100 %
b101000000000100 4
1'
#49
b10001 1
0'
#50
b111 2
b110000000000100 %
b110000000000100 4
1'
#51
b10010 1
0'
#52
1!
b1000 2
b111000000000100 %
b111000000000100 4
1'
#53
b10011 1
0'
#54
0!
1)
b1001 2
b1000000000000100 %
b1000000000000100 4
1'
#55
b10100 1
0'
#56
b0 %
b0 4
b0 2
b11 5
1'
#57
b10101 1
0'
#58
b11 3
1'
#59
b10110 1
0'
#60
b1000000 %
b1000000 4
1'
#61
b10111 1
0'
#62
b1 2
b1001000 %
b1001000 4
1'
#63
b11000 1
0'
#64
b10 2
b1000001001000 %
b1000001001000 4
1'
#65
b11001 1
0'
#66
b11 2
b10000001001000 %
b10000001001000 4
1'
#67
b11010 1
0'
#68
b100 2
b11000001001000 %
b11000001001000 4
1'
#69
b11011 1
0'
#70
b101 2
b100000001001000 %
b100000001001000 4
1'
#71
b11100 1
0'
#72
b110 2
b101000001001000 %
b101000001001000 4
1'
#73
b11101 1
0'
#74
b111 2
b110000001001000 %
b110000001001000 4
1'
#75
b11110 1
0'
#76
1"
b1000 2
b111000001001000 %
b111000001001000 4
1'
#77
b11111 1
0'
#78
0"
1*
b1001 2
b1000000001001000 %
b1000000001001000 4
1'
#79
b100000 1
0'
#80
b0 2
b1000000 %
b1000000 4
1'
#81
b100001 1
0'
#82
b100 5
b0 %
b0 4
1'
#83
b100010 1
0'
#84
b1000000 %
b1000000 4
b100 3
1'
#85
b100011 1
0'
#86
b1 2
b11100000 %
b11100000 4
1'
#87
b100100 1
0'
#88
b10 2
b1000011100000 %
b1000011100000 4
1'
#89
b100101 1
0'
#90
b11 2
b10000011100000 %
b10000011100000 4
1'
#91
b100110 1
0'
#92
b100 2
b11000011100000 %
b11000011100000 4
1'
#93
b100111 1
0'
#94
b101 2
b100000011100000 %
b100000011100000 4
1'
#95
b101000 1
0'
#96
b110 2
b101000011100000 %
b101000011100000 4
1'
#97
b101001 1
0'
#98
b111 2
b110000011100000 %
b110000011100000 4
1'
#99
b101010 1
0'
#100
1#
b1000 2
b111000011100000 %
b111000011100000 4
1'
#101
b101011 1
0'
#102
0#
1+
1,
b1001 2
b1000000011100000 %
b1000000011100000 4
1'
#103
b101100 1
0'
#104
b1000000 %
b1000000 4
b0 2
b101 5
1'
#105
b101101 1
0'
#106
b101 3
1'
#107
b101110 1
0'
#108
b110 5
1'
#109
b101111 1
0'
#110
b110 3
1'
#111
b110000 1
0'
#112
1'
#113
b110001 1
0'
#114
1'
#115
b110010 1
0'
#116
1'
#117
b110011 1
0'
#118
1'
#119
b110100 1
0'
#120
1'
#121
b110101 1
0'
#122
1'
#123
b110110 1
0'
#124
1'
#125
b110111 1
0'
#126
1'
#127
b111000 1
0'
#128
1'
#129
b111001 1
0'
#130
1'
#131
b111010 1
0'
#132
1'
#133
b111011 1
0'
#134
1'
#135
b111100 1
0'
#136
1'
#137
b111101 1
0'
#138
1'
#139
b111110 1
0'
#140
1'
#141
b111111 1
0'
#142
1'
#143
b1000000 1
0'
